{
	"info": {
		"_postman_id": "0df146b5-a75b-4d0e-9452-658f62d63f22",
		"name": "RestServicePriceProduct",
		"schema": "https://schema.getpostman.com/json/collection/v2.1.0/collection.json",
		"_exporter_id": "37729018"
	},
	"item": [
		{
			"name": "Test 1 Get Price Success",
			"request": {
				"method": "POST",
				"header": [
					{
						"key": "Content-Type",
						"value": "application/json",
						"type": "text"
					}
				],
				"body": {
					"mode": "raw",
					"raw": "{\r\n    \"application_date\": \"2020-06-14-10.00.00\",\r\n    \"id_product\": 35455,\r\n    \"id_brand\": 1\r\n}",
					"options": {
						"raw": {
							"language": "json"
						}
					}
				},
				"url": {
					"raw": "http://localhost:8081/api/prices",
					"protocol": "http",
					"host": [
						"localhost"
					],
					"port": "8081",
					"path": [
						"api",
						"prices"
					]
				}
			},
			"response": []
		},
		{
			"name": "Test 2 Get Price Success",
			"request": {
				"method": "POST",
				"header": [
					{
						"key": "Content-Type",
						"value": "application/json",
						"type": "text"
					}
				],
				"body": {
					"mode": "raw",
					"raw": "{\r\n    \"application_date\": \"2020-06-14-16.00.00\",\r\n    \"id_product\": 35455,\r\n    \"id_brand\": 1\r\n}",
					"options": {
						"raw": {
							"language": "json"
						}
					}
				},
				"url": {
					"raw": "http://localhost:8081/api/prices",
					"protocol": "http",
					"host": [
						"localhost"
					],
					"port": "8081",
					"path": [
						"api",
						"prices"
					]
				}
			},
			"response": []
		},
		{
			"name": "Test 3 Get Price Success",
			"request": {
				"method": "POST",
				"header": [
					{
						"key": "Content-Type",
						"value": "application/json",
						"type": "text"
					}
				],
				"body": {
					"mode": "raw",
					"raw": "{\r\n    \"application_date\": \"2020-06-14-21.00.00\",\r\n    \"id_product\": 35455,\r\n    \"id_brand\": 1\r\n}",
					"options": {
						"raw": {
							"language": "json"
						}
					}
				},
				"url": {
					"raw": "http://localhost:8081/api/prices",
					"protocol": "http",
					"host": [
						"localhost"
					],
					"port": "8081",
					"path": [
						"api",
						"prices"
					]
				}
			},
			"response": []
		},
		{
			"name": "Test 4 Get Price Success",
			"request": {
				"method": "POST",
				"header": [
					{
						"key": "Content-Type",
						"value": "application/json",
						"type": "text"
					}
				],
				"body": {
					"mode": "raw",
					"raw": "{\r\n    \"application_date\": \"2020-06-15-10.00.00\",\r\n    \"id_product\": 35455,\r\n    \"id_brand\": 1\r\n}",
					"options": {
						"raw": {
							"language": "json"
						}
					}
				},
				"url": {
					"raw": "http://localhost:8081/api/prices",
					"protocol": "http",
					"host": [
						"localhost"
					],
					"port": "8081",
					"path": [
						"api",
						"prices"
					]
				}
			},
			"response": []
		},
		{
			"name": "Test 5 Get Price Success",
			"request": {
				"method": "POST",
				"header": [
					{
						"key": "Content-Type",
						"value": "application/json",
						"type": "text"
					}
				],
				"body": {
					"mode": "raw",
					"raw": "{\r\n    \"application_date\": \"2020-06-16-21.00.00\",\r\n    \"id_product\": 35455,\r\n    \"id_brand\": 1\r\n}",
					"options": {
						"raw": {
							"language": "json"
						}
					}
				},
				"url": {
					"raw": "http://localhost:8081/api/prices",
					"protocol": "http",
					"host": [
						"localhost"
					],
					"port": "8081",
					"path": [
						"api",
						"prices"
					]
				}
			},
			"response": []
		},
		{
			"name": "Get No Price Success",
			"request": {
				"method": "POST",
				"header": [
					{
						"key": "Content-Type",
						"value": "application/json",
						"type": "text"
					}
				],
				"body": {
					"mode": "raw",
					"raw": "{\r\n    \"application_date\": \"2020-06-02-00.00.00\",\r\n    \"id_product\": 35455,\r\n    \"id_brand\": 1\r\n}",
					"options": {
						"raw": {
							"language": "json"
						}
					}
				},
				"url": {
					"raw": "http://localhost:8081/api/prices",
					"protocol": "http",
					"host": [
						"localhost"
					],
					"port": "8081",
					"path": [
						"api",
						"prices"
					]
				}
			},
			"response": []
		},
		{
			"name": "Get Price Format Incorrect 400",
			"request": {
				"method": "POST",
				"header": [
					{
						"key": "Content-Type",
						"value": "application/json",
						"type": "text"
					}
				],
				"body": {
					"mode": "raw",
					"raw": "{\r\n    \"application_date\": \"2020-06-15-00.00.00\",\r\n    \"id_product\": 35455,\r\n    \"id_brand\": \"L\"\r\n}",
					"options": {
						"raw": {
							"language": "json"
						}
					}
				},
				"url": {
					"raw": "http://localhost:8081/api/prices",
					"protocol": "http",
					"host": [
						"localhost"
					],
					"port": "8081",
					"path": [
						"api",
						"prices"
					]
				}
			},
			"response": []
		},
		{
			"name": "Get Price Without ID_BRAND 400",
			"request": {
				"method": "POST",
				"header": [
					{
						"key": "Content-Type",
						"value": "application/json",
						"type": "text"
					}
				],
				"body": {
					"mode": "raw",
					"raw": "{\r\n    \"application_date\": \"2020-06-15-00.00.00\",\r\n    \"id_product\": 35455\r\n}",
					"options": {
						"raw": {
							"language": "json"
						}
					}
				},
				"url": {
					"raw": "http://localhost:8081/api/prices",
					"protocol": "http",
					"host": [
						"localhost"
					],
					"port": "8081",
					"path": [
						"api",
						"prices"
					]
				}
			},
			"response": []
		},
		{
			"name": "Get Price Method Not Allowed 405",
			"protocolProfileBehavior": {
				"disableBodyPruning": true
			},
			"request": {
				"method": "GET",
				"header": [
					{
						"key": "Content-Type",
						"value": "application/json",
						"type": "text"
					}
				],
				"body": {
					"mode": "raw",
					"raw": "http://localhost:8080/api/prices",
					"options": {
						"raw": {
							"language": "json"
						}
					}
				},
				"url": {
					"raw": "http://localhost:8081/api/prices",
					"protocol": "http",
					"host": [
						"localhost"
					],
					"port": "8081",
					"path": [
						"api",
						"prices"
					]
				}
			},
			"response": []
		}
	]
}